{
  "entries": {
    "brew": {
      "curl": {
        "version": "7.74.0",
        "bottle": {
          "cellar": ":any",
          "prefix": "/usr/local",
          "files": {
            "big_sur": {
              "url": "https://homebrew.bintray.com/bottles/curl-7.74.0.big_sur.bottle.2.tar.gz",
              "sha256": "8189929ebd121b28fc04b5c93503cd7af1e3d5755ccfea080d47056e6068f86f"
            },
            "arm64_big_sur": {
              "url": "https://homebrew.bintray.com/bottles/curl-7.74.0.arm64_big_sur.bottle.2.tar.gz",
              "sha256": "0c9ae84590dcd9d4700fc2fe47badb20cdb6c948c1e351a8a588b23b11087556"
            },
            "catalina": {
              "url": "https://homebrew.bintray.com/bottles/curl-7.74.0.catalina.bottle.2.tar.gz",
              "sha256": "18e818ff24895ffd9355c34f79dd92aaf220e16d71ffdef6e2a07c0a6ddb4637"
            },
            "mojave": {
              "url": "https://homebrew.bintray.com/bottles/curl-7.74.0.mojave.bottle.2.tar.gz",
              "sha256": "eb84c59697457a6162f7275f0eff0eefc6ec03de13e467e550d35a496ca19425"
            }
          }
        }
      },
      "git": {
        "version": "2.30.0",
        "bottle": {
          "cellar": "/usr/local/Cellar",
          "prefix": "/usr/local",
          "files": {
            "big_sur": {
              "url": "https://homebrew.bintray.com/bottles/git-2.30.0.big_sur.bottle.tar.gz",
              "sha256": "bd4dd57a4740df3c596377954d45fcf2b08db83f7d8853f5361db1d158a6bdb8"
            },
            "arm64_big_sur": {
              "url": "https://homebrew.bintray.com/bottles/git-2.30.0.arm64_big_sur.bottle.tar.gz",
              "sha256": "7e0f30621e1a5be89bf604eacdca8de9a79bd16c273a1d6f4dd39c6f806d4b98"
            },
            "catalina": {
              "url": "https://homebrew.bintray.com/bottles/git-2.30.0.catalina.bottle.tar.gz",
              "sha256": "091c6e512e9dd5c3373f75a9b495dbe42f9852d93dab4c72d3fb2c8e01738953"
            },
            "mojave": {
              "url": "https://homebrew.bintray.com/bottles/git-2.30.0.mojave.bottle.tar.gz",
              "sha256": "bd96accac4e05c8799b062772ab943a10e9ff25784f2828c5c25b2debd3d2f13"
            }
          }
        }
      },
      "go": {
        "version": "1.15.6",
        "bottle": {
          "cellar": "/usr/local/Cellar",
          "prefix": "/usr/local",
          "files": {
            "big_sur": {
              "url": "https://homebrew.bintray.com/bottles/go-1.15.6.big_sur.bottle.tar.gz",
              "sha256": "2107796e255869aae4a2b1bd5766182f38c87544f968750d78b7ba520d907b1a"
            },
            "arm64_big_sur": {
              "url": "https://homebrew.bintray.com/bottles/go-1.15.6.arm64_big_sur.bottle.tar.gz",
              "sha256": "c2bd24b5a24c19bfdf97a8904aaa76c4db2a8f59096aade83310fee7af4b186c"
            },
            "catalina": {
              "url": "https://homebrew.bintray.com/bottles/go-1.15.6.catalina.bottle.tar.gz",
              "sha256": "9dac57ef268c5fee434ac7896fc77f16f16f34462822e216c9973ade6a768e0b"
            },
            "mojave": {
              "url": "https://homebrew.bintray.com/bottles/go-1.15.6.mojave.bottle.tar.gz",
              "sha256": "af0b8702944cde293206a5847bea8fb5aed66babed82fb202aff696ac5211691"
            }
          }
        }
      },
      "neovim": {
        "version": "0.4.4",
        "bottle": {
          "cellar": "/usr/local/Cellar",
          "prefix": "/usr/local",
          "files": {
            "big_sur": {
              "url": "https://homebrew.bintray.com/bottles/neovim-0.4.4.big_sur.bottle.1.tar.gz",
              "sha256": "83957460b7c664b65f7339c6e37a6b468274ca747ba8f8746616c4cebf97caa9"
            },
            "catalina": {
              "url": "https://homebrew.bintray.com/bottles/neovim-0.4.4.catalina.bottle.1.tar.gz",
              "sha256": "736260e14d50d9a42562fb0fe2215d5154a9cef3e3227469a961d030b45358fd"
            },
            "mojave": {
              "url": "https://homebrew.bintray.com/bottles/neovim-0.4.4.mojave.bottle.1.tar.gz",
              "sha256": "9f8a7cb52a0060c524d4d4f96b2590d034257cc4f255a8f05dfbf464bef29cf1"
            },
            "high_sierra": {
              "url": "https://homebrew.bintray.com/bottles/neovim-0.4.4.high_sierra.bottle.1.tar.gz",
              "sha256": "7286d497b92cf31f5839af325a1fc7760fb3006fa4a0dad7e547ab9c966cb491"
            }
          }
        }
      },
      "nvm": {
        "version": "0.37.2",
        "bottle": false
      },
      "ripgrep": {
        "version": "12.1.1",
        "bottle": {
          "cellar": ":any",
          "prefix": "/usr/local",
          "files": {
            "big_sur": {
              "url": "https://homebrew.bintray.com/bottles/ripgrep-12.1.1.big_sur.bottle.tar.gz",
              "sha256": "0ca7397f9a0ccef6cbb8ff0fd8fb18c6fe86219abaef350e3d7ef248d07440fd"
            },
            "arm64_big_sur": {
              "url": "https://homebrew.bintray.com/bottles/ripgrep-12.1.1.arm64_big_sur.bottle.tar.gz",
              "sha256": "e0147ba489a8d96e33fc8be7e2172c632075d5d31a4f6267c3606e463280e0e3"
            },
            "catalina": {
              "url": "https://homebrew.bintray.com/bottles/ripgrep-12.1.1.catalina.bottle.tar.gz",
              "sha256": "60460d422253113af3ed60332104f309638942821c655332211a6bc2213c472c"
            },
            "mojave": {
              "url": "https://homebrew.bintray.com/bottles/ripgrep-12.1.1.mojave.bottle.tar.gz",
              "sha256": "de4b18789f5d9bc4aaa4d906501200ae4ece7a1971dd1b86e2b2d0a2c8e0d764"
            },
            "high_sierra": {
              "url": "https://homebrew.bintray.com/bottles/ripgrep-12.1.1.high_sierra.bottle.tar.gz",
              "sha256": "cfea5335bf4eccfb7cd1d93bec234d96bd49dce8d593ea966687f777909ba291"
            }
          }
        }
      },
      "ruby": {
        "version": "3.0.0_1",
        "bottle": {
          "cellar": "/usr/local/Cellar",
          "prefix": "/usr/local",
          "files": {
            "big_sur": {
              "url": "https://homebrew.bintray.com/bottles/ruby-3.0.0_1.big_sur.bottle.tar.gz",
              "sha256": "14e41a492db72e630df763af44be0ae0026ba034be02d8092ce9e485a4cf2658"
            },
            "arm64_big_sur": {
              "url": "https://homebrew.bintray.com/bottles/ruby-3.0.0_1.arm64_big_sur.bottle.tar.gz",
              "sha256": "063dae2750c25110b82fa3965d3c62217dd60a2e61730697dc9925c3ba153cf3"
            },
            "catalina": {
              "url": "https://homebrew.bintray.com/bottles/ruby-3.0.0_1.catalina.bottle.tar.gz",
              "sha256": "163da02e9cb0d551dfdc8f5ccb7b3c97e698cbe1db7c6dc8ee87b8c5f717ce09"
            },
            "mojave": {
              "url": "https://homebrew.bintray.com/bottles/ruby-3.0.0_1.mojave.bottle.tar.gz",
              "sha256": "52e37187871e0b486d255524d25a1e5b55176fe3a598d04b768ffd65d913338a"
            }
          }
        }
      },
      "tig": {
        "version": "2.5.1",
        "bottle": {
          "cellar": ":any",
          "prefix": "/usr/local",
          "files": {
            "big_sur": {
              "url": "https://homebrew.bintray.com/bottles/tig-2.5.1.big_sur.bottle.tar.gz",
              "sha256": "5a7ab3c18f11a0a2e0517648ab884ae245483f095c8397d67550cec98b661d37"
            },
            "arm64_big_sur": {
              "url": "https://homebrew.bintray.com/bottles/tig-2.5.1.arm64_big_sur.bottle.tar.gz",
              "sha256": "8981a3341850eec12635de144174fab3198f73b530ed5979413334ddeabf0bf7"
            },
            "catalina": {
              "url": "https://homebrew.bintray.com/bottles/tig-2.5.1.catalina.bottle.tar.gz",
              "sha256": "e3dd84d1883ca04013d72311c248f623a3e55fa8fa31456f5fe956ae19ccd4de"
            },
            "mojave": {
              "url": "https://homebrew.bintray.com/bottles/tig-2.5.1.mojave.bottle.tar.gz",
              "sha256": "0fbc0ae28aed58f73b1e798cbe75c8d131762c91371bd00e5a257c3a6fda7f85"
            },
            "high_sierra": {
              "url": "https://homebrew.bintray.com/bottles/tig-2.5.1.high_sierra.bottle.tar.gz",
              "sha256": "9f6983f67cbbe6d551c8ab39131ca1e91e9f3e57ffe1f1791e6c182fd017fbf8"
            }
          }
        }
      },
      "vim": {
        "version": "8.2.2300",
        "bottle": {
          "cellar": "/usr/local/Cellar",
          "prefix": "/usr/local",
          "files": {
            "big_sur": {
              "url": "https://homebrew.bintray.com/bottles/vim-8.2.2300.big_sur.bottle.tar.gz",
              "sha256": "5f850477c11a6b036a78278e0050f9de3033d7532d352565fc30d18d0184721c"
            },
            "arm64_big_sur": {
              "url": "https://homebrew.bintray.com/bottles/vim-8.2.2300.arm64_big_sur.bottle.tar.gz",
              "sha256": "32b310f3772fa023216c250fd7dc5aba5624e6ca62473537198c5609f633b2e9"
            },
            "catalina": {
              "url": "https://homebrew.bintray.com/bottles/vim-8.2.2300.catalina.bottle.tar.gz",
              "sha256": "143bbd20d066609bc66784bd1bbd2b4c0abf99cb81a1503667aded50aff9b923"
            },
            "mojave": {
              "url": "https://homebrew.bintray.com/bottles/vim-8.2.2300.mojave.bottle.tar.gz",
              "sha256": "967a88f53158d9d7705a28fa142b661fb9b93adea0eab97e801913bf9024d63e"
            }
          }
        }
      },
      "wget": {
        "version": "1.21",
        "bottle": {
          "cellar": "/usr/local/Cellar",
          "prefix": "/usr/local",
          "files": {
            "big_sur": {
              "url": "https://homebrew.bintray.com/bottles/wget-1.21.big_sur.bottle.tar.gz",
              "sha256": "eb830909eed1e6d861968f324fd0701883df44f9d6e191c4e5ebbe2635cc70e7"
            },
            "arm64_big_sur": {
              "url": "https://homebrew.bintray.com/bottles/wget-1.21.arm64_big_sur.bottle.tar.gz",
              "sha256": "2824baa832bb6abe003371d42bab24df5afab5e4076922b2300a90a98526990b"
            },
            "catalina": {
              "url": "https://homebrew.bintray.com/bottles/wget-1.21.catalina.bottle.tar.gz",
              "sha256": "d163d32bba98f0a535d179c5d8efd076d12f41bd9232f5c0a41523a4eeaeb500"
            },
            "mojave": {
              "url": "https://homebrew.bintray.com/bottles/wget-1.21.mojave.bottle.tar.gz",
              "sha256": "6343b9c76468bf9ba05e587403b378b1bb93e5108c6505abef4eaaee92257e22"
            }
          }
        }
      },
      "zsh": {
        "version": "5.8_1",
        "bottle": {
          "cellar": "/usr/local/Cellar",
          "prefix": "/usr/local",
          "files": {
            "big_sur": {
              "url": "https://homebrew.bintray.com/bottles/zsh-5.8_1.big_sur.bottle.tar.gz",
              "sha256": "a93717bcbb1a41829ac7549f7dea0e2be4bb11985be734f03801150338d6b8e6"
            },
            "arm64_big_sur": {
              "url": "https://homebrew.bintray.com/bottles/zsh-5.8_1.arm64_big_sur.bottle.tar.gz",
              "sha256": "01ae59e3ea21dd7691120aec89552e4f4c10c6489a24b9cc23256129e3cbe7b6"
            },
            "catalina": {
              "url": "https://homebrew.bintray.com/bottles/zsh-5.8_1.catalina.bottle.tar.gz",
              "sha256": "aaf19f69f79ac2ef80ff31d3b2f0017f400bf40022f8626d5ae046990961a5f5"
            },
            "mojave": {
              "url": "https://homebrew.bintray.com/bottles/zsh-5.8_1.mojave.bottle.tar.gz",
              "sha256": "a40a54e4b686eb75f04e7dcc57391245a4f6b08a39825f7f6ebc9f76ebcbff46"
            },
            "high_sierra": {
              "url": "https://homebrew.bintray.com/bottles/zsh-5.8_1.high_sierra.bottle.tar.gz",
              "sha256": "edfbc09a9571fadf351e0f94e545a88aa33763518a3330c0bae497a6a259d63f"
            }
          }
        }
      },
      "mas": {
        "version": "1.7.1",
        "bottle": {
          "cellar": ":any",
          "prefix": "/usr/local",
          "files": {
            "big_sur": {
              "url": "https://homebrew.bintray.com/bottles/mas-1.7.1.big_sur.bottle.tar.gz",
              "sha256": "432091a534d0a1f753fcf953fb1c20c10ef5762b7f8922cb378c3dcd36898d30"
            },
            "catalina": {
              "url": "https://homebrew.bintray.com/bottles/mas-1.7.1.catalina.bottle.tar.gz",
              "sha256": "e6de2f98ebd21885a9827664fe1b7eea5516a7fd75d5b7383e3a9b088591a27f"
            },
            "mojave": {
              "url": "https://homebrew.bintray.com/bottles/mas-1.7.1.mojave.bottle.tar.gz",
              "sha256": "8b6dc4e261ebdc8e2f93afe87da3db4d482eb3d8a0358ab19a0485d434550e77"
            }
          }
        }
      },
      "tree": {
        "version": "1.8.0",
        "bottle": {
          "cellar": ":any_skip_relocation",
          "prefix": "/usr/local",
          "files": {
            "big_sur": {
              "url": "https://homebrew.bintray.com/bottles/tree-1.8.0.big_sur.bottle.tar.gz",
              "sha256": "572adeaba1ffee7fa8bcad414c8b18140c367bbc81dc2ab8fd438cbd7e4a985b"
            },
            "arm64_big_sur": {
              "url": "https://homebrew.bintray.com/bottles/tree-1.8.0.arm64_big_sur.bottle.tar.gz",
              "sha256": "b9d1925b5b306e098ff43f1ce5fc409b759c6d2d468e20af5628797a56234c4f"
            },
            "catalina": {
              "url": "https://homebrew.bintray.com/bottles/tree-1.8.0.catalina.bottle.tar.gz",
              "sha256": "18f7984bdbab22251e9fc3c7832dbace5c7f7a77e8d63717bb0078385e2bf255"
            },
            "mojave": {
              "url": "https://homebrew.bintray.com/bottles/tree-1.8.0.mojave.bottle.tar.gz",
              "sha256": "7152288c457dd893de50fa9d6ac9a8599748564e1b3586eec8eff7057089051a"
            },
            "high_sierra": {
              "url": "https://homebrew.bintray.com/bottles/tree-1.8.0.high_sierra.bottle.tar.gz",
              "sha256": "107d965994381d34e90b58a62f1c306c1b8a698db2696cdd905ba65c801ecc3b"
            },
            "sierra": {
              "url": "https://homebrew.bintray.com/bottles/tree-1.8.0.sierra.bottle.tar.gz",
              "sha256": "07d980571469a0cc699c69a8726eee338f782ba61c041e58f01ddb2924d08aeb"
            }
          }
        }
      },
      "fish": {
        "version": "3.1.2",
        "bottle": {
          "cellar": ":any_skip_relocation",
          "prefix": "/usr/local",
          "files": {
            "big_sur": {
              "url": "https://homebrew.bintray.com/bottles/fish-3.1.2.big_sur.bottle.tar.gz",
              "sha256": "ef7f5a2fd69ba2baed78d02ee162cc8fb85644161dd765d47b570b56db9569cf"
            },
            "arm64_big_sur": {
              "url": "https://homebrew.bintray.com/bottles/fish-3.1.2.arm64_big_sur.bottle.tar.gz",
              "sha256": "b1257836de799a5204be8289bde8008b616c2fc070b22fec914e044f0a4bd8f2"
            },
            "catalina": {
              "url": "https://homebrew.bintray.com/bottles/fish-3.1.2.catalina.bottle.tar.gz",
              "sha256": "b158b7f8640feb7c622ff3ca92b1bd88565f274f3e761499f5926bb124eeff7d"
            },
            "mojave": {
              "url": "https://homebrew.bintray.com/bottles/fish-3.1.2.mojave.bottle.tar.gz",
              "sha256": "6797636eaba364d0cbbc0459103a8767598e985f01846cca6cb57c986dfee7b8"
            },
            "high_sierra": {
              "url": "https://homebrew.bintray.com/bottles/fish-3.1.2.high_sierra.bottle.tar.gz",
              "sha256": "2609577a0d9f6b661331adccf5d1d8e010662ffe128869757e0af9a6760e26fb"
            }
          }
        }
      },
      "tmux": {
        "version": "3.1c_1",
        "bottle": {
          "cellar": ":any",
          "prefix": "/usr/local",
          "files": {
            "big_sur": {
              "url": "https://homebrew.bintray.com/bottles/tmux-3.1c_1.big_sur.bottle.tar.gz",
              "sha256": "6f9b667c08719ca7a164c571740d510236d55c922058b1d71fb38f66163a394e"
            },
            "arm64_big_sur": {
              "url": "https://homebrew.bintray.com/bottles/tmux-3.1c_1.arm64_big_sur.bottle.tar.gz",
              "sha256": "b24cedca1ea1e8e343e5faf6acb509e3df2b3d91b6dcb2934b2c697d8d5b6b07"
            },
            "catalina": {
              "url": "https://homebrew.bintray.com/bottles/tmux-3.1c_1.catalina.bottle.tar.gz",
              "sha256": "e1148f3043ef1e77e942bc654e6b3867f40401b0ba93e6d44a460467c51e0a3b"
            },
            "mojave": {
              "url": "https://homebrew.bintray.com/bottles/tmux-3.1c_1.mojave.bottle.tar.gz",
              "sha256": "3ba85f3524acbf5e1fb04135fa9b7f2bbdd5d3c8ed94189685be50ca19722bbe"
            },
            "high_sierra": {
              "url": "https://homebrew.bintray.com/bottles/tmux-3.1c_1.high_sierra.bottle.tar.gz",
              "sha256": "ec5fcbdc337221efdbf3f21121fb087b998dd7d3bf6dd5bb72e352d9c9463a57"
            }
          }
        }
      }
    },
    "tap": {
      "homebrew/cask": {
        "revision": "3d3c93c640208424c85f223c60c41bdf35ecf2aa"
      }
    },
    "cask": {
      "alfred": {
        "version": "4.1.1_1172",
        "options": {
          "full_name": "alfred"
        }
      },
      "alt-tab": {
        "version": "6.6.0",
        "options": {
          "full_name": "alt-tab"
        }
      },
      "browserosaurus": {
        "version": "12.0.2",
        "options": {
          "full_name": "browserosaurus"
        }
      },
      "caffeine": {
        "version": "1.1.3",
        "options": {
          "full_name": "caffeine"
        }
      },
      "firefox-beta": {
        "version": "latest",
        "options": {
          "full_name": "firefox-beta"
        }
      },
      "font-hack-nerd-font": {
        "version": "2.1.0",
        "options": {
          "full_name": "font-hack-nerd-font"
        }
      },
      "gpg-suite": {
        "version": "2020.1",
        "options": {
          "full_name": "gpg-suite"
        }
      },
      "iterm2": {
        "version": "3.3.12",
        "options": {
          "full_name": "iterm2"
        }
      },
      "keka-beta": {
        "version": "1.2.0-beta.2",
        "options": {
          "full_name": "keka-beta"
        }
      },
      "kekadefaultapp": {
        "version": "1.1.22,1.0.1-r.7",
        "options": {
          "full_name": "kekadefaultapp"
        }
      },
      "paw": {
        "version": "3.1.10",
        "options": {
          "full_name": "paw"
        }
      },
      "reaper": {
        "version": "6.19.0,6.19",
        "options": {
          "full_name": "reaper"
        }
      },
      "rectangle": {
        "version": "0.31",
        "options": {
          "full_name": "rectangle"
        }
      },
      "signal": {
        "version": "1.34.5",
        "options": {
          "full_name": "signal"
        }
      },
      "slack": {
        "version": "4.7.0",
        "options": {
          "full_name": "slack"
        }
      },
      "spotify": {
        "version": "latest",
        "options": {
          "full_name": "spotify"
        }
      },
      "steam": {
        "version": "2.0",
        "options": {
          "full_name": "steam"
        }
      },
      "telegram": {
        "version": "6.2.5.203437",
        "options": {
          "full_name": "telegram"
        }
      },
      "visual-studio-code": {
        "version": "1.49.0",
        "options": {
          "full_name": "visual-studio-code"
        }
      },
      "whatsapp": {
        "version": "2.2029.4",
        "options": {
          "full_name": "whatsapp"
        }
      }
    },
    "mas": {
      "1Password": {
        "id": "443987910",
        "version": "6.8.9"
      },
      "1Password 7": null,
      "Clocker": {
        "id": "1056643111",
        "version": "20.07.01"
      },
      "GarageBand": {
        "id": "682658836",
        "version": "10.4.2"
      },
      "Keynote": {
        "id": "409183694",
        "version": "10.3.8"
      },
      "Numbers": {
        "id": "409203825",
        "version": "10.3.5"
      },
      "Pages": {
        "id": "409201541",
        "version": "10.3.5"
      },
      "Simplenote": {
        "id": "692867256",
        "version": "2.5"
      },
      "Todoist": {
        "id": "585829637",
        "version": "7.5"
      },
      "Amphetamine": {
        "id": "937984704",
        "version": "5.1.1"
      }
    }
  },
  "system": {
    "macos": {
      "catalina": {
        "HOMEBREW_VERSION": "2.5.1",
        "HOMEBREW_PREFIX": "/usr/local",
        "Homebrew/homebrew-core": "756ffabae87ecac456a85ab28a44f144590eaf33",
        "CLT": "12.0.0.0.1.1597368733",
        "Xcode": "12.0",
        "macOS": "10.15.6"
      },
      "big_sur": {
        "HOMEBREW_VERSION": "2.7.1",
        "HOMEBREW_PREFIX": "/usr/local",
        "Homebrew/homebrew-core": "eb3250c061f1bb6764be295902541529d8e807df",
        "CLT": "12.0.32.21",
        "Xcode": "11.7",
        "macOS": "11.1"
      }
    }
  }
}
